src/__init__.py
src/app.py
src/low_n/__init__.py
src/low_n/app.py
src/low_n/database/__init__.py
src/low_n/database/app.py
src/low_n/dataset_analysis/__init__.py
src/low_n/dataset_analysis/app.py
src/low_n/directed_evolution/__init__.py
src/low_n/directed_evolution/app.py
src/low_n/evotuning/__init__.py
src/low_n/evotuning/amino_acid_example.py
src/low_n/evotuning/app.py
src/low_n/evotuning/dataset.py
src/low_n/evotuning/example.py
src/low_n/evotuning/train.py
src/low_n/evotuning/transform.py
src/low_n/jackhmmr/__init__.py
src/low_n/jackhmmr/app.py
src/low_n/jackhmmr/database.py
src/low_n/jackhmmr/parse_results.py
src/low_n/jackhmmr/search.py
src/low_n/projects/__init__.py
src/low_n/projects/app.py
src/low_n/projects/utils.py
src/low_n/topmodel/__init__.py
src/low_n/topmodel/app.py
src/low_n/topmodel/topmodel.py
src/low_n/zero_shot/__init__.py
src/low_n/zero_shot/app.py
src/low_n/zero_shot/zero_shot_model.py
src/shuffle/__init__.py
src/shuffle/app.py
src/shuffle/src/__init__.py
src/shuffle/src/codon_table.py
src/shuffle/src/dna_from_alignment.py
src/shuffle/src/hit_storage.py
src/shuffle/src/restriction_enzyme_hit.py
src/shuffle/src/restriction_enzymes.py
src/shuffle/src/restriction_site_finder.py
src/shuffle/src/reverse_translate.py
src/shuffle/src/utils.py
src/shuffle/src/validation.py
src/shuffle/tests/__init__.py
src/shuffle/tests/test_dna_from_alignment.py
src/shuffle/tests/test_restriction_site_finder.py
src/shuffle/tests/test_reverse_translate.py
seq_mutator-1.0.0.dist-info/LICENSE
seq_mutator-1.0.0.dist-info/METADATA
seq_mutator-1.0.0.dist-info/WHEEL
seq_mutator-1.0.0.dist-info/entry_points.txt
seq_mutator-1.0.0.dist-info/top_level.txt
seq_mutator-1.0.0.dist-info/RECORD
