Metadata-Version: 2.1
Name: seq-mutator
Version: 1.0.0
Summary: A toolbox for protein engineering and DNA shuffling
Home-page: https://gitlab.igem.org/2024/software-tools/unimuenster
Author: iGEM Team Muenster 2024
Author-email: j_albr16@uni-muenster.de
License: UNKNOWN
Platform: UNKNOWN
Requires-Python: >=3.10.11,<=3.10.12
License-File: LICENSE
Requires-Dist: Levenshtein==0.25.1
Requires-Dist: accelerate==0.33.0
Requires-Dist: biopython==1.84
Requires-Dist: datasets==2.21.0
Requires-Dist: numpy==1.26.4
Requires-Dist: pandas==2.2.2
Requires-Dist: peft==0.12.0
Requires-Dist: pynvml==11.5.3
Requires-Dist: scikit-learn==1.5.1
Requires-Dist: scipy==1.14.1
Requires-Dist: tensorboard==2.17.1
Requires-Dist: tokenizers==0.19.1
Requires-Dist: torch==2.0.1
Requires-Dist: tqdm==4.66.5
Requires-Dist: transformers==4.44.2
Requires-Dist: typer==0.12.5
